fastapi_pretty_errors/__init__.py
fastapi_pretty_errors/middleware.py
fastapi_pretty_errors-0.1.1.dist-info/LICENSE
fastapi_pretty_errors-0.1.1.dist-info/METADATA
fastapi_pretty_errors-0.1.1.dist-info/WHEEL
fastapi_pretty_errors-0.1.1.dist-info/RECORD
