Metadata-Version: 2.1
Name: fastapi-pretty-errors
Version: 0.1.1
Summary: A FastAPI middleware to prettify exceptions using PrettyErrors.
Home-page: https://github.com/savvan0h/fastapi-pretty-errors
License: MIT
Author: Hiroki Sawano
Author-email: hiroki.sawano.2512@gmail.com
Requires-Python: >=3.9,<4.0
Classifier: License :: OSI Approved :: MIT License
Classifier: Programming Language :: Python :: 3
Classifier: Programming Language :: Python :: 3.9
Classifier: Programming Language :: Python :: 3.10
Classifier: Programming Language :: Python :: 3.11
Classifier: Programming Language :: Python :: 3.12
Requires-Dist: fastapi (>=0.87)
Requires-Dist: pretty-errors (>=1.2.25,<2.0.0)
Project-URL: Repository, https://github.com/savvan0h/fastapi-pretty-errors
